LICENSE
MANIFEST.in
README.md
VERSION
requirements.txt
setup.cfg
setup.py
dvdp.ha_mqtt.egg-info/PKG-INFO
dvdp.ha_mqtt.egg-info/SOURCES.txt
dvdp.ha_mqtt.egg-info/dependency_links.txt
dvdp.ha_mqtt.egg-info/requires.txt
dvdp.ha_mqtt.egg-info/top_level.txt
dvdp/ha_mqtt/__init__.py
dvdp/ha_mqtt/__main__.py
dvdp/ha_mqtt/client.py
dvdp/ha_mqtt/light.py
dvdp/ha_mqtt/message_queue.py