Metadata-Version: 2.1
Name: dvdp.ha-mqtt
Version: 0.2.3
Summary: Home assistant mqtt devices interface
Home-page: https://github.com/davidvdp/ha_mqtt
Author: David van der Pol
Author-email: david@davidvanderpol.com
License: MIT
Download-URL: https://github.com/davidvdp/ha_mqtt/archive/v0.2.3.tar.gz
Keywords: MQTT,Home,Assistant
Platform: UNKNOWN
Classifier: Intended Audience :: Developers
Classifier: License :: OSI Approved :: MIT License
Classifier: Programming Language :: Python :: 3
Classifier: Programming Language :: Python :: 3.7
